AUTHORS.txt
LICENSE.txt
MANIFEST.in
README.md
setup.py
PyGB.egg-info/PKG-INFO
PyGB.egg-info/SOURCES.txt
PyGB.egg-info/dependency_links.txt
PyGB.egg-info/requires.txt
PyGB.egg-info/top_level.txt
docs/Makefile
docs/conf.py
docs/index.rst
docs/install.rst
docs/keyboard.rst
docs/make.bat
docs/mouse.rst
docs/quickstart.rst
docs/roadmap.rst
docs/screenshot.rst
docs/tests.rst
docs/source/modules.rst
docs/source/pyautogui.rst
pygb/__init__.py
pygb/__main__.py
pygb/_pygb_java.py
pygb/_pygb_osx.py
pygb/_pygb_screen.py
pygb/_pygb_win.py
pygb/_pygb_x11.py
tests/test_pyautogui.py
tests/test_pygb_macos.py